flory/__init__.py
flory/_version.py
flory/shortcut.py
flory/common/__init__.py
flory/common/exceptions.py
flory/common/phases.py
flory/common/utilities.py
flory/constraint/__init__.py
flory/constraint/base.py
flory/constraint/linear_global.py
flory/constraint/linear_local.py
flory/constraint/no.py
flory/ensemble/__init__.py
flory/ensemble/base.py
flory/ensemble/canonical.py
flory/ensemble/grandcanonical.py
flory/entropy/__init__.py
flory/entropy/base.py
flory/entropy/ideal_gas.py
flory/entropy/ideal_gas_polydispersed.py
flory/free_energy/__init__.py
flory/free_energy/base.py
flory/free_energy/flory_huggins.py
flory/interaction/__init__.py
flory/interaction/base.py
flory/interaction/flory_huggins.py
flory/interaction/flory_huggins_block.py
flory/mcmp/__init__.py
flory/mcmp/_finder_impl.py
flory/mcmp/finder.py
flory-0.2.0.dist-info/LICENSE
flory-0.2.0.dist-info/METADATA
flory-0.2.0.dist-info/WHEEL
flory-0.2.0.dist-info/top_level.txt
flory-0.2.0.dist-info/RECORD
