Metadata-Version: 2.1
Name: flory
Version: 0.2.0
Summary: Python package for finding coexisting phases in multicomponent mixtures
Author-email: Yicheng Qiang <yicheng.qiang@ds.mpg.de>
License: MIT License
Project-URL: homepage, https://github.com/qiangyicheng/flory
Project-URL: documentation, https://flory.readthedocs.io
Project-URL: repository, https://github.com/qiangyicheng/flory
Keywords: physics,phase-separation,free-energy
Classifier: Development Status :: 4 - Beta
Classifier: Intended Audience :: Science/Research
Classifier: Topic :: Scientific/Engineering
Classifier: License :: OSI Approved :: MIT License
Classifier: Programming Language :: Python :: 3
Classifier: Programming Language :: Python :: 3.9
Classifier: Programming Language :: Python :: 3.10
Classifier: Programming Language :: Python :: 3.11
Classifier: Programming Language :: Python :: 3.12
Requires-Python: >=3.9
License-File: LICENSE
Requires-Dist: numba >=0.57
Requires-Dist: numpy >=1.22
Requires-Dist: scipy >=1.7
Requires-Dist: tqdm >=4.60
Provides-Extra: dev
Requires-Dist: pytest >=6.2 ; extra == 'dev'
Requires-Dist: pytest-cov >=4.0 ; extra == 'dev'
Requires-Dist: matplotlib >=3.1 ; extra == 'dev'
Requires-Dist: Sphinx >=4 ; extra == 'dev'
Requires-Dist: sphinx-autodoc-typehints >=2.2 ; extra == 'dev'
Requires-Dist: sphinx-paramlinks >=0.6 ; extra == 'dev'
Requires-Dist: sphinx-rtd-theme >=2.0 ; extra == 'dev'
Requires-Dist: docutils ; extra == 'dev'
Requires-Dist: more-itertools ; extra == 'dev'
